{
  "operationId": "GetContainerLogsDeployedOnNode",
  "description": "This example shows how to get last 10 lines of container logs for container deployed on a Service Fabric node for the given code package.",
  "parameters": {
    "api-version": "6.2",
    "nodeName": "_Node_0",
    "applicationId": "SimpleHttpServerApp",
    "ServiceManifestName": "SimpleHttpServerSvcPkg",
    "CodePackageName": "Code",
    "Tail": "10"
  },
  "responses": {
    "200": {
      "headers": {
      },
      "body": {
        "Content": "UTC Time Now: 04\/02\/2018 22:019.11\r\nUTC Time Now: 04\/02\/2018 22:019.12\r\nUTC Time Now: 04\/02\/2018 22:019.13\r\nUTC Time Now: 04\/02\/2018 22:019.144\r\nUTC Time Now: 04\/02\/2018 22:019.15\r\nUTC Time Now: 04\/02\/2018 22:019.16\r\nUTC Time Now: 04\/02\/2018 22:019.17\r\nUTC Time Now: 04\/02\/2018 22:019.18\r\nUTC Time Now: 04\/02\/2018 22:019.19\r\nUTC Time Now: 04\/02\/2018 22:06:40\r\n"
      }
    }
  }
}